Metadata-Version: 2.1
Name: vlogin
Version: 0.0.2
Summary: vac
Home-page: UNKNOWN
Author: Wind
Author-email: jinghaozhehh@163.com
License: UNKNOWN
Platform: UNKNOWN
Classifier: Programming Language :: Python :: 3
Classifier: License :: OSI Approved :: MIT License
Classifier: Operating System :: OS Independent
